telethoncosmosdb/__init__.py
telethoncosmosdb/telethoncosmosdb.py
telethon_cosmosdb_sqlsession-0.1.1.dist-info/LICENSE
telethon_cosmosdb_sqlsession-0.1.1.dist-info/METADATA
telethon_cosmosdb_sqlsession-0.1.1.dist-info/WHEEL
telethon_cosmosdb_sqlsession-0.1.1.dist-info/top_level.txt
telethon_cosmosdb_sqlsession-0.1.1.dist-info/RECORD
