Metadata-Version: 2.1
Name: telethon-cosmosdb-sqlsession
Version: 0.1.1
Summary: A Telethon session storage that runs on Azure Cosmos DB (SQL API)
Home-page: https://github.com/ivanmak/telethon-cosmosdb-sqlsession/
Author: Ivan Mak
Author-email: ivan.mak@icloud.com
License: UNKNOWN
Platform: UNKNOWN
Classifier: Development Status :: 4 - Beta
Classifier: Programming Language :: Python :: 3
Classifier: Programming Language :: Python :: 3.5
Classifier: Programming Language :: Python :: 3.6
Classifier: Programming Language :: Python :: 3.7
Classifier: Programming Language :: Python :: 3.8
Classifier: License :: OSI Approved :: MIT License
Classifier: Operating System :: OS Independent
Classifier: Topic :: Communications :: Chat
Requires-Python: >=3.6
Requires-Dist: azure-cosmos
Requires-Dist: telethon (>=1.11.3)
